CHANGES.txt
LICENSE.txt
MANIFEST.in
README.txt
setup.py
js/__init__.py
js.jquery_timeentry.egg-info/PKG-INFO
js.jquery_timeentry.egg-info/SOURCES.txt
js.jquery_timeentry.egg-info/dependency_links.txt
js.jquery_timeentry.egg-info/entry_points.txt
js.jquery_timeentry.egg-info/namespace_packages.txt
js.jquery_timeentry.egg-info/not-zip-safe
js.jquery_timeentry.egg-info/requires.txt
js.jquery_timeentry.egg-info/top_level.txt
js/jquery_timeentry/__init__.py
js/jquery_timeentry/test_jquery_time_entry.txt
js/jquery_timeentry/resources/jquery.timeentry-ca.js
js/jquery_timeentry/resources/jquery.timeentry-cs.js
js/jquery_timeentry/resources/jquery.timeentry-de.js
js/jquery_timeentry/resources/jquery.timeentry-es.js
js/jquery_timeentry/resources/jquery.timeentry-fa.js
js/jquery_timeentry/resources/jquery.timeentry-fr.js
js/jquery_timeentry/resources/jquery.timeentry-hu.js
js/jquery_timeentry/resources/jquery.timeentry-is.js
js/jquery_timeentry/resources/jquery.timeentry-it.js
js/jquery_timeentry/resources/jquery.timeentry-ja.js
js/jquery_timeentry/resources/jquery.timeentry-lt.js
js/jquery_timeentry/resources/jquery.timeentry-lv.js
js/jquery_timeentry/resources/jquery.timeentry-nl.js
js/jquery_timeentry/resources/jquery.timeentry-pl.js
js/jquery_timeentry/resources/jquery.timeentry-pt.js
js/jquery_timeentry/resources/jquery.timeentry-ro.js
js/jquery_timeentry/resources/jquery.timeentry-ru.js
js/jquery_timeentry/resources/jquery.timeentry-sk.js
js/jquery_timeentry/resources/jquery.timeentry-sv.js
js/jquery_timeentry/resources/jquery.timeentry-tr.js
js/jquery_timeentry/resources/jquery.timeentry-vi.js
js/jquery_timeentry/resources/jquery.timeentry-zh-CN.js
js/jquery_timeentry/resources/jquery.timeentry-zh-TW.js
js/jquery_timeentry/resources/jquery.timeentry.css
js/jquery_timeentry/resources/jquery.timeentry.js
js/jquery_timeentry/resources/jquery.timeentry.min.js
js/jquery_timeentry/resources/spinnerBlue.png
js/jquery_timeentry/resources/spinnerBlueBig.png
js/jquery_timeentry/resources/spinnerDefault.png
js/jquery_timeentry/resources/spinnerDefaultBig.png
js/jquery_timeentry/resources/spinnerGem.png
js/jquery_timeentry/resources/spinnerGemBig.png
js/jquery_timeentry/resources/spinnerGreen.png
js/jquery_timeentry/resources/spinnerGreenBig.png
js/jquery_timeentry/resources/spinnerOrange.png
