Metadata-Version: 1.0
Name: js.jquery-timeentry
Version: 1.5.0
Summary: Fanstatic packaging of jQuery Time Entry
Home-page: UNKNOWN
Author: Fanstatic Developers
Author-email: fanstatic@googlegroups.com
License: BSD
Platform: UNKNOWN
